[
  {
    "id": 0,
    "title": "",
    "description": "* 일정 기간동안 발생한 TRANSACTIONS이 많은 순으로 정산",
    "items": [
      {
        "ranking": "1",
        "rankingChange": 4,
        "name": "P05 Piccadilly circus",
        "collectionName": "London Underground Station(LUS) 264 Genesis",
        "img": "/img/banner/img_A02_Aldgate.png",
        "link": "/marketplace/collection",
        "price": "1,000,000",
        "priceChange": 24.5
      },
      {
        "ranking": "2",
        "rankingChange": -4,
        "name": "abcdefghijklnmopqrstuvwxyz abcdefghijklnmopqrstuvwxyz",
        "collectionName": "abcdefghijklnmopqrstuvwxyzabcdefghijklnmopqrstuvwxyz",
        "img": "/img/banner/img_A02_Aldgate.png",
        "link": "/marketplace/collection",
        "price": "1,000,000",
        "priceChange": -24.5
      },
      {
        "ranking": "3",
        "rankingChange": -4,
        "name": "abcdefghijklnmopqrstuvwxyz abcdefghijklnmopqrstuvwxyz",
        "collectionName": "abcdefghijklnmopqrstuvwxyzabcdefghijklnmopqrstuvwxyz",
        "img": "/img/banner/img_A02_Aldgate.png",
        "link": "/marketplace/collection",
        "price": "1,000,000",
        "priceChange": -24.5
      },
      {
        "ranking": "4",
        "name": "abcdefghijklnmopqrstuvwxyz abcdefghijklnmopqrstuvwxyz",
        "collectionName": "abcdefghijklnmopqrstuvwxyzabcdefghijklnmopqrstuvwxyz",
        "img": "/img/banner/img_A02_Aldgate.png",
        "link": "/marketplace/collection",
        "price": "1,000,000",
        "priceChange": -24.5
      },
      {
        "ranking": "5",
        "name": "abcdefghijklnmopqrstuvwxyz abcdefghijklnmopqrstuvwxyz",
        "collectionName": "abcdefghijklnmopqrstuvwxyzabcdefghijklnmopqrstuvwxyz",
        "img": "/img/banner/img_A02_Aldgate.png",
        "link": "/marketplace/collection",
        "price": "1,000,000",
        "priceChange": -24.5
      },
      {
        "ranking": "6",
        "name": "abcdefghijklnmopqrstuvwxyz abcdefghijklnmopqrstuvwxyz",
        "collectionName": "abcdefghijklnmopqrstuvwxyzabcdefghijklnmopqrstuvwxyz",
        "img": "/img/banner/img_A02_Aldgate.png",
        "link": "/marketplace/collection",
        "price": "1,000,000",
        "priceChange": -24.5
      },
      {
        "ranking": "7",
        "name": "abcdefghijklnmopqrstuvwxyz abcdefghijklnmopqrstuvwxyz",
        "collectionName": "abcdefghijklnmopqrstuvwxyzabcdefghijklnmopqrstuvwxyz",
        "img": "/img/banner/img_A02_Aldgate.png",
        "link": "/marketplace/collection",
        "price": "1,000,000",
        "priceChange": -24.5
      },
      {
        "ranking": "8",
        "name": "abcdefghijklnmopqrstuvwxyz abcdefghijklnmopqrstuvwxyz",
        "collectionName": "abcdefghijklnmopqrstuvwxyzabcdefghijklnmopqrstuvwxyz",
        "img": "/img/banner/img_A02_Aldgate.png",
        "link": "/marketplace/collection",
        "price": "1,000,000",
        "priceChange": -24.5
      },
      {
        "ranking": "9",
        "name": "abcdefghijklnmopqrstuvwxyz abcdefghijklnmopqrstuvwxyz",
        "collectionName": "abcdefghijklnmopqrstuvwxyzabcdefghijklnmopqrstuvwxyz",
        "img": "/img/banner/img_A02_Aldgate.png",
        "link": "/marketplace/collection",
        "price": "1,000,000",
        "priceChange": -24.5
      },
      {
        "ranking": "10",
        "name": "abcdefghijklnmopqrstuvwxyz abcdefghijklnmopqrstuvwxyz",
        "collectionName": "abcdefghijklnmopqrstuvwxyzabcdefghijklnmopqrstuvwxyz",
        "img": "/img/banner/img_A02_Aldgate.png",
        "link": "/marketplace/collection",
        "price": "1,000,000",
        "priceChange": -24.5
      }
    ]
  },
  {
    "id": 1,
    "title": "",
    "items": [
      {
        "ranking": "1",
        "rankingChange": 4,
        "name": "P05 Piccadilly circus",
        "collectionName": "London Underground Station(LUS) 264 Genesis",
        "img": "/img/banner/img_A02_Aldgate.png",
        "link": "/marketplace/collection",
        "transitionDay": 1234
      },
      {
        "ranking": "2",
        "rankingChange": -4,
        "name": "abcdefghijklnmopqrstuvwxyz abcdefghijklnmopqrstuvwxyz",
        "collectionName": "abcdefghijklnmopqrstuvwxyzabcdefghijklnmopqrstuvwxyz",
        "img": "/img/banner/img_A02_Aldgate.png",
        "link": "/marketplace/collection",
        "price": "1,000,000",
        "transitionDay": 1234
      },
      {
        "ranking": "3",
        "rankingChange": -4,
        "name": "abcdefghijklnmopqrstuvwxyz abcdefghijklnmopqrstuvwxyz",
        "collectionName": "abcdefghijklnmopqrstuvwxyzabcdefghijklnmopqrstuvwxyz",
        "img": "/img/banner/img_A02_Aldgate.png",
        "link": "/marketplace/collection",
        "transitionDay": 1234
      },
      {
        "ranking": "4",
        "name": "abcdefghijklnmopqrstuvwxyz abcdefghijklnmopqrstuvwxyz",
        "collectionName": "abcdefghijklnmopqrstuvwxyzabcdefghijklnmopqrstuvwxyz",
        "img": "/img/banner/img_A02_Aldgate.png",
        "link": "/marketplace/collection",
        "transitionDay": 1234
      },
      {
        "ranking": "5",
        "name": "abcdefghijklnmopqrstuvwxyz abcdefghijklnmopqrstuvwxyz",
        "collectionName": "abcdefghijklnmopqrstuvwxyzabcdefghijklnmopqrstuvwxyz",
        "img": "/img/banner/img_A02_Aldgate.png",
        "link": "/marketplace/collection",
        "transitionDay": 1234
      },
      {
        "ranking": "6",
        "name": "abcdefghijklnmopqrstuvwxyz abcdefghijklnmopqrstuvwxyz",
        "collectionName": "abcdefghijklnmopqrstuvwxyzabcdefghijklnmopqrstuvwxyz",
        "img": "/img/banner/img_A02_Aldgate.png",
        "link": "/marketplace/collection",
        "transitionDay": 1234
      },
      {
        "ranking": "7",
        "name": "abcdefghijklnmopqrstuvwxyz abcdefghijklnmopqrstuvwxyz",
        "collectionName": "abcdefghijklnmopqrstuvwxyzabcdefghijklnmopqrstuvwxyz",
        "img": "/img/banner/img_A02_Aldgate.png",
        "link": "/marketplace/collection",
        "transitionDay": 1234
      },
      {
        "ranking": "8",
        "name": "abcdefghijklnmopqrstuvwxyz abcdefghijklnmopqrstuvwxyz",
        "collectionName": "abcdefghijklnmopqrstuvwxyzabcdefghijklnmopqrstuvwxyz",
        "img": "/img/banner/img_A02_Aldgate.png",
        "link": "/marketplace/collection",
        "transitionDay": 1234
      },
      {
        "ranking": "9",
        "name": "abcdefghijklnmopqrstuvwxyz abcdefghijklnmopqrstuvwxyz",
        "collectionName": "abcdefghijklnmopqrstuvwxyzabcdefghijklnmopqrstuvwxyz",
        "img": "/img/banner/img_A02_Aldgate.png",
        "link": "/marketplace/collection",
        "transitionDay": 1234
      },
      {
        "ranking": "10",
        "name": "abcdefghijklnmopqrstuvwxyz abcdefghijklnmopqrstuvwxyz",
        "collectionName": "abcdefghijklnmopqrstuvwxyzabcdefghijklnmopqrstuvwxyz",
        "img": "/img/banner/img_A02_Aldgate.png",
        "link": "/marketplace/collection",
        "transitionDay": 1234
      }
    ]
  }
]
